flask_register.py
setup.py
Flask_Register.egg-info/PKG-INFO
Flask_Register.egg-info/SOURCES.txt
Flask_Register.egg-info/dependency_links.txt
Flask_Register.egg-info/not-zip-safe
Flask_Register.egg-info/requires.txt
Flask_Register.egg-info/top_level.txt